setup.py
dsnd_probabilityAC/Binomialdistribution.py
dsnd_probabilityAC/Gaussiandistribution.py
dsnd_probabilityAC/Generaldistribution.py
dsnd_probabilityAC/__init__.py
dsnd_probabilityAC.egg-info/PKG-INFO
dsnd_probabilityAC.egg-info/SOURCES.txt
dsnd_probabilityAC.egg-info/dependency_links.txt
dsnd_probabilityAC.egg-info/not-zip-safe
dsnd_probabilityAC.egg-info/top_level.txt