Metadata-Version: 1.0
Name: dsnd-probabilityAC
Version: 1.0
Summary: Gaussian and Binomial distributions
Home-page: UNKNOWN
Author: Adriana Chavez
Author-email: UNKNOWN
License: UNKNOWN
Platform: UNKNOWN
